{"text": " You don't know, babe When you hold me And kiss me slowly It's the sweetest thing And it don't change If I had it my way You would know that you are You're the coffee that I need in the morning You're my sunshine in the rain when it's pouring Won't you give yourself to me? Give it all I just wanna see I just wanna see How beautiful you are You know that I see it I know you're a star Where you go I'll follow No matter how far If life is a movie You know you're the best part You're the best part You're the best part You're the best part You're the best part You're the best part You're the best part You're the one that I desire When we wake up And then we make love It makes me feel so nice You're my water when I'm stuck in the desert You're the talent all I take when my head hurts You're the sunshine of my life I just wanna see how beautiful you are You know that I see it, I know you're a star Where you go I'll follow, no matter how far If life is a movie then you're the best part Oh, you're the best part Oh, best part If you love me won't you say something If you love me won't you say something If you love me won't you If you love me won't you Love me won't you If you love me won't you If you love me, won't ya Ah If you love me, won't ya Say something If you love me, won't ya Say something If you love me, won't ya I will just Ah, ah, ah, ah", "segments": [{"id": 0, "seek": 0, "start": 0.0, "end": 16.92, "text": " You don't know, babe", "tokens": [50365, 509, 500, 380, 458, 11, 24655, 51211], "temperature": 0.0, "avg_logprob": -0.39365069930617874, "compression_ratio": 1.1111111111111112, "no_speech_prob": 2.1866437480144718e-11}, {"id": 1, "seek": 0, "start": 16.92, "end": 20.14, "text": " When you hold me", "tokens": [51211, 1133, 291, 1797, 385, 51372], "temperature": 0.0, "avg_logprob": -0.39365069930617874, "compression_ratio": 1.1111111111111112, "no_speech_prob": 2.1866437480144718e-11}, {"id": 2, "seek": 0, "start": 20.14, "end": 22.64, "text": " And kiss me slowly", "tokens": [51372, 400, 7704, 385, 5692, 51497], "temperature": 0.0, "avg_logprob": -0.39365069930617874, "compression_ratio": 1.1111111111111112, "no_speech_prob": 2.1866437480144718e-11}, {"id": 3, "seek": 0, "start": 22.64, "end": 25.64, "text": " It's the sweetest thing", "tokens": [51497, 467, 311, 264, 3844, 377, 551, 51647], "temperature": 0.0, "avg_logprob": -0.39365069930617874, "compression_ratio": 1.1111111111111112, "no_speech_prob": 2.1866437480144718e-11}, {"id": 4, "seek": 0, "start": 25.64, "end": 29.64, "text": " And it don't change", "tokens": [51647, 400, 309, 500, 380, 1319, 51847], "temperature": 0.0, "avg_logprob": -0.39365069930617874, "compression_ratio": 1.1111111111111112, "no_speech_prob": 2.1866437480144718e-11}, {"id": 5, "seek": 2964, "start": 29.64, "end": 32.8, "text": " If I had it my way", "tokens": [50365, 759, 286, 632, 309, 452, 636, 50523], "temperature": 0.0, "avg_logprob": -0.28318435267398234, "compression_ratio": 1.551948051948052, "no_speech_prob": 8.690359196150688e-12}, {"id": 6, "seek": 2964, "start": 32.8, "end": 36.9, "text": " You would know that you are", "tokens": [50523, 509, 576, 458, 300, 291, 366, 50728], "temperature": 0.0, "avg_logprob": -0.28318435267398234, "compression_ratio": 1.551948051948052, "no_speech_prob": 8.690359196150688e-12}, {"id": 7, "seek": 2964, "start": 36.9, "end": 42.260000000000005, "text": " You're the coffee that I need in the morning", "tokens": [50728, 509, 434, 264, 4982, 300, 286, 643, 294, 264, 2446, 50996], "temperature": 0.0, "avg_logprob": -0.28318435267398234, "compression_ratio": 1.551948051948052, "no_speech_prob": 8.690359196150688e-12}, {"id": 8, "seek": 2964, "start": 42.260000000000005, "end": 45.480000000000004, "text": " You're my sunshine in the rain when it's pouring", "tokens": [50996, 509, 434, 452, 25219, 294, 264, 4830, 562, 309, 311, 20450, 51157], "temperature": 0.0, "avg_logprob": -0.28318435267398234, "compression_ratio": 1.551948051948052, "no_speech_prob": 8.690359196150688e-12}, {"id": 9, "seek": 2964, "start": 45.480000000000004, "end": 47.86, "text": " Won't you give yourself to me?", "tokens": [51157, 14710, 380, 291, 976, 1803, 281, 385, 30, 51276], "temperature": 0.0, "avg_logprob": -0.28318435267398234, "compression_ratio": 1.551948051948052, "no_speech_prob": 8.690359196150688e-12}, {"id": 10, "seek": 2964, "start": 48.22, "end": 50.08, "text": " Give it all", "tokens": [51294, 5303, 309, 439, 51387], "temperature": 0.0, "avg_logprob": -0.28318435267398234, "compression_ratio": 1.551948051948052, "no_speech_prob": 8.690359196150688e-12}, {"id": 11, "seek": 2964, "start": 50.08, "end": 52.78, "text": " I just wanna see", "tokens": [51387, 286, 445, 1948, 536, 51522], "temperature": 0.0, "avg_logprob": -0.28318435267398234, "compression_ratio": 1.551948051948052, "no_speech_prob": 8.690359196150688e-12}, {"id": 12, "seek": 2964, "start": 52.78, "end": 55.400000000000006, "text": " I just wanna see", "tokens": [51522, 286, 445, 1948, 536, 51653], "temperature": 0.0, "avg_logprob": -0.28318435267398234, "compression_ratio": 1.551948051948052, "no_speech_prob": 8.690359196150688e-12}, {"id": 13, "seek": 2964, "start": 55.400000000000006, "end": 59.260000000000005, "text": " How beautiful you are", "tokens": [51653, 1012, 2238, 291, 366, 51846], "temperature": 0.0, "avg_logprob": -0.28318435267398234, "compression_ratio": 1.551948051948052, "no_speech_prob": 8.690359196150688e-12}, {"id": 14, "seek": 5926, "start": 59.26, "end": 62.42, "text": " You know that I see it", "tokens": [50365, 509, 458, 300, 286, 536, 309, 50523], "temperature": 0.0, "avg_logprob": -0.13404933214187623, "compression_ratio": 0.7333333333333333, "no_speech_prob": 1.2138988599030842e-11}, {"id": 15, "seek": 6242, "start": 62.42, "end": 65.58, "text": " I know you're a star", "tokens": [50365, 286, 458, 291, 434, 257, 3543, 50523], "temperature": 0.0, "avg_logprob": -0.13551199436187744, "compression_ratio": 0.7142857142857143, "no_speech_prob": 1.1570221343515374e-11}, {"id": 16, "seek": 6558, "start": 65.58, "end": 68.74, "text": " Where you go I'll follow", "tokens": [50365, 2305, 291, 352, 286, 603, 1524, 50523], "temperature": 0.0, "avg_logprob": -0.17443387508392333, "compression_ratio": 0.75, "no_speech_prob": 1.2740475341388446e-11}, {"id": 17, "seek": 6874, "start": 68.74, "end": 71.89999999999999, "text": " No matter how far", "tokens": [50365, 883, 1871, 577, 1400, 50523], "temperature": 0.0, "avg_logprob": -0.21024875342845917, "compression_ratio": 0.68, "no_speech_prob": 1.3810701714189744e-11}, {"id": 18, "seek": 7190, "start": 71.9, "end": 75.06, "text": " If life is a movie", "tokens": [50365, 759, 993, 307, 257, 3169, 50523], "temperature": 0.0, "avg_logprob": -0.10904313458336724, "compression_ratio": 0.6923076923076923, "no_speech_prob": 1.7871948712611108e-11}, {"id": 19, "seek": 7506, "start": 75.06, "end": 78.22, "text": " You know you're the best part", "tokens": [50365, 509, 458, 291, 434, 264, 1151, 644, 50523], "temperature": 0.0, "avg_logprob": -0.4150196838378906, "compression_ratio": 1.7317073170731707, "no_speech_prob": 1.3976611534793904e-11}, {"id": 20, "seek": 7506, "start": 78.22, "end": 84.22, "text": " You're the best part", "tokens": [50523, 509, 434, 264, 1151, 644, 50823], "temperature": 0.0, "avg_logprob": -0.4150196838378906, "compression_ratio": 1.7317073170731707, "no_speech_prob": 1.3976611534793904e-11}, {"id": 21, "seek": 7506, "start": 84.22, "end": 85.22, "text": " You're the best part", "tokens": [50823, 509, 434, 264, 1151, 644, 50873], "temperature": 0.0, "avg_logprob": -0.4150196838378906, "compression_ratio": 1.7317073170731707, "no_speech_prob": 1.3976611534793904e-11}, {"id": 22, "seek": 8522, "start": 85.22, "end": 88.38, "text": " You're the best part", "tokens": [50365, 509, 434, 264, 1151, 644, 50523], "temperature": 0.0, "avg_logprob": -0.5160230398178101, "compression_ratio": 1.28125, "no_speech_prob": 3.3450592989980876e-11}, {"id": 23, "seek": 8522, "start": 88.38, "end": 92.38, "text": " You're the best part", "tokens": [50523, 509, 434, 264, 1151, 644, 50723], "temperature": 0.0, "avg_logprob": -0.5160230398178101, "compression_ratio": 1.28125, "no_speech_prob": 3.3450592989980876e-11}, {"id": 24, "seek": 9238, "start": 92.38, "end": 95.53999999999999, "text": " You're the best part", "tokens": [50365, 509, 434, 264, 1151, 644, 50523], "temperature": 0.8, "avg_logprob": -0.6351339817047119, "compression_ratio": 1.28125, "no_speech_prob": 2.6427103561044163e-11}, {"id": 25, "seek": 9238, "start": 95.53999999999999, "end": 96.64, "text": " You're the best part", "tokens": [50523, 509, 434, 264, 1151, 644, 50578], "temperature": 0.8, "avg_logprob": -0.6351339817047119, "compression_ratio": 1.28125, "no_speech_prob": 2.6427103561044163e-11}, {"id": 26, "seek": 9664, "start": 96.64, "end": 102.64, "text": " You're the one that I desire", "tokens": [50365, 509, 434, 264, 472, 300, 286, 7516, 50665], "temperature": 0.0, "avg_logprob": -0.1510087539409769, "compression_ratio": 1.4375, "no_speech_prob": 8.595921197063205e-11}, {"id": 27, "seek": 9664, "start": 102.64, "end": 106.64, "text": " When we wake up", "tokens": [50665, 1133, 321, 6634, 493, 50865], "temperature": 0.0, "avg_logprob": -0.1510087539409769, "compression_ratio": 1.4375, "no_speech_prob": 8.595921197063205e-11}, {"id": 28, "seek": 9664, "start": 106.64, "end": 110.64, "text": " And then we make love", "tokens": [50865, 400, 550, 321, 652, 959, 51065], "temperature": 0.0, "avg_logprob": -0.1510087539409769, "compression_ratio": 1.4375, "no_speech_prob": 8.595921197063205e-11}, {"id": 29, "seek": 9664, "start": 110.64, "end": 114.64, "text": " It makes me feel so nice", "tokens": [51065, 467, 1669, 385, 841, 370, 1481, 51265], "temperature": 0.0, "avg_logprob": -0.1510087539409769, "compression_ratio": 1.4375, "no_speech_prob": 8.595921197063205e-11}, {"id": 30, "seek": 9664, "start": 114.64, "end": 118.64, "text": " You're my water when I'm stuck in the desert", "tokens": [51265, 509, 434, 452, 1281, 562, 286, 478, 5541, 294, 264, 11029, 51465], "temperature": 0.0, "avg_logprob": -0.1510087539409769, "compression_ratio": 1.4375, "no_speech_prob": 8.595921197063205e-11}, {"id": 31, "seek": 9664, "start": 118.64, "end": 122.64, "text": " You're the talent all I take when my head hurts", "tokens": [51465, 509, 434, 264, 8301, 439, 286, 747, 562, 452, 1378, 11051, 51665], "temperature": 0.0, "avg_logprob": -0.1510087539409769, "compression_ratio": 1.4375, "no_speech_prob": 8.595921197063205e-11}, {"id": 32, "seek": 12264, "start": 122.64, "end": 129.64, "text": " You're the sunshine of my life", "tokens": [50365, 509, 434, 264, 25219, 295, 452, 993, 50715], "temperature": 0.0, "avg_logprob": -0.06669561716974998, "compression_ratio": 1.3057851239669422, "no_speech_prob": 5.375630496295969e-12}, {"id": 33, "seek": 12264, "start": 129.64, "end": 135.64, "text": " I just wanna see how beautiful you are", "tokens": [50715, 286, 445, 1948, 536, 577, 2238, 291, 366, 51015], "temperature": 0.0, "avg_logprob": -0.06669561716974998, "compression_ratio": 1.3057851239669422, "no_speech_prob": 5.375630496295969e-12}, {"id": 34, "seek": 12264, "start": 135.64, "end": 142.64, "text": " You know that I see it, I know you're a star", "tokens": [51015, 509, 458, 300, 286, 536, 309, 11, 286, 458, 291, 434, 257, 3543, 51365], "temperature": 0.0, "avg_logprob": -0.06669561716974998, "compression_ratio": 1.3057851239669422, "no_speech_prob": 5.375630496295969e-12}, {"id": 35, "seek": 12264, "start": 142.64, "end": 148.64, "text": " Where you go I'll follow, no matter how far", "tokens": [51365, 2305, 291, 352, 286, 603, 1524, 11, 572, 1871, 577, 1400, 51665], "temperature": 0.0, "avg_logprob": -0.06669561716974998, "compression_ratio": 1.3057851239669422, "no_speech_prob": 5.375630496295969e-12}, {"id": 36, "seek": 14864, "start": 148.64, "end": 155.64, "text": " If life is a movie then you're the best part", "tokens": [50365, 759, 993, 307, 257, 3169, 550, 291, 434, 264, 1151, 644, 50715], "temperature": 0.0, "avg_logprob": -0.14631500244140624, "compression_ratio": 1.4821428571428572, "no_speech_prob": 4.849206539786488e-12}, {"id": 37, "seek": 14864, "start": 155.64, "end": 161.64, "text": " Oh, you're the best part", "tokens": [50715, 876, 11, 291, 434, 264, 1151, 644, 51015], "temperature": 0.0, "avg_logprob": -0.14631500244140624, "compression_ratio": 1.4821428571428572, "no_speech_prob": 4.849206539786488e-12}, {"id": 38, "seek": 14864, "start": 161.64, "end": 167.64, "text": " Oh, best part", "tokens": [51015, 876, 11, 1151, 644, 51315], "temperature": 0.0, "avg_logprob": -0.14631500244140624, "compression_ratio": 1.4821428571428572, "no_speech_prob": 4.849206539786488e-12}, {"id": 39, "seek": 16764, "start": 167.64, "end": 174.64, "text": " If you love me won't you say something", "tokens": [50365, 759, 291, 959, 385, 1582, 380, 291, 584, 746, 50715], "temperature": 0.0, "avg_logprob": -0.2926637759575477, "compression_ratio": 0.8837209302325582, "no_speech_prob": 1.281858213325604e-11}, {"id": 40, "seek": 17464, "start": 174.64, "end": 175.64, "text": " If you love me won't you say something", "tokens": [50365, 759, 291, 959, 385, 1582, 380, 291, 584, 746, 50415], "temperature": 1.0, "avg_logprob": -0.28776221579693734, "compression_ratio": 2.519230769230769, "no_speech_prob": 1.5222987800878052e-11}, {"id": 41, "seek": 17464, "start": 175.64, "end": 177.64, "text": " If you love me won't you", "tokens": [50415, 759, 291, 959, 385, 1582, 380, 291, 50515], "temperature": 1.0, "avg_logprob": -0.28776221579693734, "compression_ratio": 2.519230769230769, "no_speech_prob": 1.5222987800878052e-11}, {"id": 42, "seek": 17464, "start": 177.64, "end": 178.64, "text": " If you love me won't you", "tokens": [50515, 759, 291, 959, 385, 1582, 380, 291, 50565], "temperature": 1.0, "avg_logprob": -0.28776221579693734, "compression_ratio": 2.519230769230769, "no_speech_prob": 1.5222987800878052e-11}, {"id": 43, "seek": 17464, "start": 178.64, "end": 179.64, "text": " Love me won't you", "tokens": [50565, 5956, 385, 1582, 380, 291, 50615], "temperature": 1.0, "avg_logprob": -0.28776221579693734, "compression_ratio": 2.519230769230769, "no_speech_prob": 1.5222987800878052e-11}, {"id": 44, "seek": 17464, "start": 179.64, "end": 181.64, "text": " If you love me won't you", "tokens": [50615, 759, 291, 959, 385, 1582, 380, 291, 50715], "temperature": 1.0, "avg_logprob": -0.28776221579693734, "compression_ratio": 2.519230769230769, "no_speech_prob": 1.5222987800878052e-11}, {"id": 45, "seek": 18164, "start": 181.64, "end": 183.27999999999997, "text": " If you love me, won't ya", "tokens": [50365, 759, 291, 959, 385, 11, 1582, 380, 2478, 50447], "temperature": 1.0, "avg_logprob": -1.1526976994105749, "compression_ratio": 2.1846153846153844, "no_speech_prob": 5.1280851093293833e-11}, {"id": 46, "seek": 18164, "start": 183.27999999999997, "end": 186.72, "text": " Ah If you love me, won't ya", "tokens": [50447, 2438, 759, 291, 959, 385, 11, 1582, 380, 2478, 50619], "temperature": 1.0, "avg_logprob": -1.1526976994105749, "compression_ratio": 2.1846153846153844, "no_speech_prob": 5.1280851093293833e-11}, {"id": 47, "seek": 18164, "start": 186.72, "end": 198.35999999999999, "text": " Say something", "tokens": [50619, 6463, 746, 51201], "temperature": 1.0, "avg_logprob": -1.1526976994105749, "compression_ratio": 2.1846153846153844, "no_speech_prob": 5.1280851093293833e-11}, {"id": 48, "seek": 18164, "start": 198.35999999999999, "end": 201.94, "text": " If you love me, won't ya", "tokens": [51201, 759, 291, 959, 385, 11, 1582, 380, 2478, 51380], "temperature": 1.0, "avg_logprob": -1.1526976994105749, "compression_ratio": 2.1846153846153844, "no_speech_prob": 5.1280851093293833e-11}, {"id": 49, "seek": 18164, "start": 201.94, "end": 202.82, "text": " Say something", "tokens": [51380, 6463, 746, 51424], "temperature": 1.0, "avg_logprob": -1.1526976994105749, "compression_ratio": 2.1846153846153844, "no_speech_prob": 5.1280851093293833e-11}, {"id": 50, "seek": 18164, "start": 202.82, "end": 204.23999999999998, "text": " If you love me, won't ya", "tokens": [51424, 759, 291, 959, 385, 11, 1582, 380, 2478, 51495], "temperature": 1.0, "avg_logprob": -1.1526976994105749, "compression_ratio": 2.1846153846153844, "no_speech_prob": 5.1280851093293833e-11}, {"id": 51, "seek": 18164, "start": 204.23999999999998, "end": 205.79999999999998, "text": " I will just", "tokens": [51495, 286, 486, 445, 51573], "temperature": 1.0, "avg_logprob": -1.1526976994105749, "compression_ratio": 2.1846153846153844, "no_speech_prob": 5.1280851093293833e-11}, {"id": 52, "seek": 20580, "start": 205.8, "end": 235.78, "text": " Ah, ah, ah, ah", "tokens": [50365, 2438, 11, 3716, 11, 3716, 11, 3716, 51864], "temperature": 0.0, "avg_logprob": -0.585667896270752, "compression_ratio": 1.0, "no_speech_prob": 2.670623167055908e-10}], "language": "en"}